{
  "type": "Feature",
  "properties": {
    "gn:country":"TK",
    "gn:fcode":"ATOL",
    "gn:pop":426,
    "iso:country":"TK",
    "name:unk_x_variant":[
        "Nukuno"
    ],
    "qs:name":"Nukunonu Atoll",
    "qs:photos_9r":0,
    "qs:photos_sr":0,
    "qs:pop_sr":"2",
    "wof:name":"Nukunonu Atoll",
    "wof:placetype":"locality",
    "wof:population":426
},
  "geometry": {"coordinates":[-171.82900000000001,-9.169],"type":"Point"}
}